uptogithub/__init__.py
uptogithub/setup.py
uptogithub/x.usramp.py
uptogithub/usramp/__init__.py
uptogithub/usramp/usramplib.py
usramp/__init__.py
usramp/usramplib.py
usramp-0.1.data/scripts/x.usramp.py
usramp-0.1.dist-info/METADATA
usramp-0.1.dist-info/WHEEL
usramp-0.1.dist-info/top_level.txt
usramp-0.1.dist-info/RECORD
