Metadata-Version: 2.1
Name: usramp
Version: 0.1
Summary: Ultrafast shape-recognition algorithm with mass ponderation
Home-page: https://github.com/fortizchi/usramp
Author: Filiberto Ortiz-Chi, Jose Aminadat Morato Marquez, Srinivas Godavarthi, Claudia Guadalupe Espinosa Gonzalez, and Jose Gilberto Torres-Torres
Author-email: fortiz666@gmail.com
License: None
Classifier: Programming Language :: Python :: 3
Classifier: Operating System :: OS Independent
Requires-Python: >=3.5
Requires-Dist: numpy
